pyitm/__init__.py
pyitm/itm.py
pyitm/util.py
pyitm-0.3.dist-info/LICENSE
pyitm-0.3.dist-info/METADATA
pyitm-0.3.dist-info/WHEEL
pyitm-0.3.dist-info/top_level.txt
pyitm-0.3.dist-info/RECORD
