Metadata-Version: 2.1
Name: pyitm
Version: 0.3
Summary: Longley-Rice Irregular Terrain Model
Home-page: https://github.com/tmd224/pyitm
Author: Mike DiSanto
Author-email: tmdisanto@gmail.com
License: MIT
Download-URL: https://github.com/tmd224/pyitm/archive/v0.3.tar.gz
Keywords: Longley-Rice,ITM,RF Propagation,Terrain
Platform: UNKNOWN
Classifier: Development Status :: 3 - Alpha
Classifier: Intended Audience :: Science/Research
Classifier: License :: OSI Approved :: MIT License
Classifier: Operating System :: Microsoft
Classifier: Operating System :: POSIX :: Linux
Classifier: Programming Language :: Python :: 3.4
Classifier: Programming Language :: Python :: 3.5
Classifier: Programming Language :: Python :: 3.6
Classifier: Programming Language :: Python :: 3.7
Classifier: Programming Language :: Python :: 3.8
Classifier: Topic :: Scientific/Engineering
License-File: LICENSE
